translation_hub/__init__.py
translation_hub/api.py
translation_hub/config.py
translation_hub/exceptions.py
translation_hub/validator_handler.py
translation_hub/apis/__init__.py
translation_hub/apis/aliyun_api.py
translation_hub/apis/baidu_api.py
translation_hub/apis/baidu_free_api.py
translation_hub/apis/bing_free_api.py
translation_hub/apis/deepl_api.py
translation_hub/apis/google_free_api.py
translation_hub/apis/sogou_free_api.py
translation_hub/apis/tencent_api.py
translation_hub/apis/youdao_api.py
translation_hub/core/__init__.py
translation_hub/core/enums.py
translation_hub/core/paths.py
translation_hub/utils/__init__.py
translation_hub/utils/config.py
translation_hub/utils/requests.py
translation_hub/validators/__init__.py
translation_hub/validators/content_validator.py
translation_hub/validators/secret_key_validator.py
translation_hub/validators/validator.py
translation_hub-0.12.4.dist-info/METADATA
translation_hub-0.12.4.dist-info/WHEEL
translation_hub-0.12.4.dist-info/RECORD
