Metadata-Version: 2.4
Name: translation_hub
Version: 0.12.4
Summary: 没有任何依赖的翻译库，API 统一简单易用，适合快速集成翻译功能而不想引入庞大的依赖库
Project-URL: Homepage, https://github.com/271374667/translation_hub
Project-URL: Source Code, https://github.com/271374667/translation_hub
Author-email: PythonImporter <271374667@qq.com>
Requires-Python: >=3.10
Requires-Dist: requests>=2.32.3
